thumbor_cloud_storage/__init__.py
thumbor_cloud_storage/loaders/__init__.py
thumbor_cloud_storage/loaders/cloud_storage_loader.py
thumbor_cloud_storage/result_storages/__init__.py
thumbor_cloud_storage/result_storages/cloud_storage.py
thumbor_cloud_storage-3.0.0.dist-info/DESCRIPTION.rst
thumbor_cloud_storage-3.0.0.dist-info/LICENSE.txt
thumbor_cloud_storage-3.0.0.dist-info/METADATA
thumbor_cloud_storage-3.0.0.dist-info/RECORD
thumbor_cloud_storage-3.0.0.dist-info/WHEEL
thumbor_cloud_storage-3.0.0.dist-info/metadata.json
thumbor_cloud_storage-3.0.0.dist-info/top_level.txt
