Metadata-Version: 2.0
Name: thumbor-cloud-storage
Version: 3.0.0
Summary: Google Cloud Storage loader and result storage for Thumbor
Home-page: https://github.com/superbalist/thumbor-cloud-storage/
Author: Superbalist Engineering
Author-email: tech@superbalist.com
License: MIT
Keywords: thumbor,google cloud platform,gcloud,imaging,thumbnail,imagemagick
Platform: UNKNOWN
Classifier: Development Status :: 5 - Production/Stable
Classifier: Intended Audience :: Developers
Classifier: Natural Language :: English
Classifier: License :: OSI Approved :: MIT License
Classifier: Operating System :: OS Independent
Classifier: Programming Language :: Python
Classifier: Programming Language :: Python :: 2
Classifier: Programming Language :: Python :: 2.7
Classifier: Programming Language :: Python :: 3
Classifier: Programming Language :: Python :: 3.4
Classifier: Programming Language :: Python :: 3.5
Classifier: Programming Language :: Python :: Implementation :: CPython
Classifier: Programming Language :: Python :: Implementation :: PyPy
Classifier: Topic :: Software Development :: Libraries :: Python Modules
Requires-Dist: gcloud (>=0.18.3)
Requires-Dist: thumbor (>=6.3.1)
